insightsolver/__init__.py
insightsolver/api_utilities.py
insightsolver/insightsolver.py
insightsolver/version.py
insightsolver/visualization.py
insightsolver/assets/__init__.py
insightsolver/assets/google_fonts_icons/LICENSE
insightsolver/assets/google_fonts_icons/OFL.txt
insightsolver/assets/google_fonts_icons/README.md
insightsolver/assets/google_fonts_icons/Roboto-Bold.ttf
insightsolver/assets/google_fonts_icons/Roboto-Regular.ttf
insightsolver/assets/google_fonts_icons/__init__.py
insightsolver/assets/google_fonts_icons/png/__init__.py
insightsolver/assets/google_fonts_icons/png/attach_money.png
insightsolver/assets/google_fonts_icons/png/gondola_lift.png
insightsolver/assets/google_fonts_icons/png/network_intelligence.png
insightsolver/assets/google_fonts_icons/png/offline_bolt.png
insightsolver/assets/google_fonts_icons/png/select_all.png
insightsolver/assets/google_fonts_icons/png/sell.png
insightsolver/assets/google_fonts_icons/png/shuffle.png
insightsolver/assets/google_fonts_icons/png/timelapse.png
insightsolver/assets/google_fonts_icons/png/zoom_out_map.png
insightsolver-0.1.83.dist-info/licenses/LICENSE
insightsolver-0.1.83.dist-info/METADATA
insightsolver-0.1.83.dist-info/WHEEL
insightsolver-0.1.83.dist-info/top_level.txt
insightsolver-0.1.83.dist-info/RECORD
