Metadata-Version: 2.4
Name: insightsolver
Version: 0.1.83
Summary: InsightSolver offers rule-based insights generation for actionable data-driven decisions.
Author-email: Noé Aubin-Cadot <noe.aubin-cadot@insightsolver.com>
Maintainer-email: "InsightSolver Solutions Inc." <support@insightsolver.com>
License: Apache-2.0
Project-URL: Homepage, https://insightsolver.com
Project-URL: Repository, https://github.com/insightsolver/insightsolver
Project-URL: Documentation, https://insightsolver.readthedocs.io
Keywords: data-science,rule-mining,machine-learning,interpretable-ai,decision-intelligence
Classifier: Development Status :: 4 - Beta
Classifier: Intended Audience :: Developers
Classifier: Intended Audience :: Science/Research
Classifier: Programming Language :: Python :: 3
Classifier: Programming Language :: Python :: 3.9
Classifier: Programming Language :: Python :: 3.10
Classifier: Programming Language :: Python :: 3.11
Classifier: Programming Language :: Python :: 3.12
Classifier: Operating System :: OS Independent
Classifier: Topic :: Scientific/Engineering :: Artificial Intelligence
Requires-Python: >=3.9
License-File: LICENSE
Requires-Dist: pandas>=2.2.2
Requires-Dist: numpy>=2.0.0
Requires-Dist: requests>=2.32.3
Requires-Dist: google-auth>=2.6.0
Requires-Dist: cryptography>=43.0.0
Requires-Dist: mpmath>=1.3.0
Requires-Dist: urllib3>=2.0.2
Requires-Dist: idna>=2.10
Requires-Dist: Pillow
Requires-Dist: matplotlib
Requires-Dist: seaborn
Requires-Dist: scikit-learn
Requires-Dist: openpyxl
Requires-Dist: statsmodels
Provides-Extra: dev
Requires-Dist: pytest>=7.0; extra == "dev"
Requires-Dist: pytest-mock; extra == "dev"
Requires-Dist: ruff>=0.1.0; extra == "dev"
Requires-Dist: mypy>=1.0; extra == "dev"
Requires-Dist: pandas-stubs; extra == "dev"
Requires-Dist: types-requests; extra == "dev"
Dynamic: license-file
